simple_python_couch_db/__init__.py
simple_python_couch_db/couch.py
simple_python_couch_db-0.1.1.dist-info/LICENSE
simple_python_couch_db-0.1.1.dist-info/METADATA
simple_python_couch_db-0.1.1.dist-info/WHEEL
simple_python_couch_db-0.1.1.dist-info/top_level.txt
simple_python_couch_db-0.1.1.dist-info/RECORD
