Metadata-Version: 2.1
Name: simple-python-couch-db
Version: 0.1.1
Summary: Simple adapter to use CouchDB with Python.
Home-page: https://github.com/bjoerndot/simple-python-couch-db
Author: Oliver Schwamb
Author-email: mail@oliverschwamb.de
License: UNKNOWN
Platform: UNKNOWN
Classifier: License :: OSI Approved :: MIT License
Classifier: Operating System :: OS Independent
Classifier: Programming Language :: Python :: 3
Classifier: Programming Language :: Python :: 3.6
Classifier: Topic :: Database :: Front-Ends
Requires-Python: >=3.6
Requires-Dist: requests
